MANIFEST.in
setup.py
./django_analysis_tool/__init__.py
./django_analysis_tool/manage.py
./django_analysis_tool/run.py
./django_analysis_tool/base/__init__.py
./django_analysis_tool/base/analyzer.py
./django_analysis_tool/base/scanner.py
./django_analysis_tool/base/token.py
./django_analysis_tool/base/utils.py
./django_analysis_tool/base/workflow.py
./django_analysis_tool/base/xls.py
./django_analysis_tool/base/demo/__init__.py
./django_analysis_tool/base/demo/collect_performance_csv.py
./django_analysis_tool/base/demo/demo.py
./django_analysis_tool/base/demo/demo_count_thread.py
./django_analysis_tool/base/demo/jsonchinese.py
./django_analysis_tool/base/demo/multiprocessthread.py
./django_analysis_tool/base/extractions/__init__.py
./django_analysis_tool/base/extractions/outzip.py
./django_analysis_tool/base/utility/__init__.py
./django_analysis_tool/base/utility/construct.py
./django_analysis_tool/lab/__init__.py
./django_analysis_tool/lab/settings.py
./django_analysis_tool/lab/urls.py
./django_analysis_tool/lab/wsgi.py
./django_analysis_tool/lab_analysis_tools/__init__.py
./django_analysis_tool/lab_analysis_tools/admin.py
./django_analysis_tool/lab_analysis_tools/apps.py
./django_analysis_tool/lab_analysis_tools/forms.py
./django_analysis_tool/lab_analysis_tools/models.py
./django_analysis_tool/lab_analysis_tools/tests.py
./django_analysis_tool/lab_analysis_tools/urls.py
./django_analysis_tool/lab_analysis_tools/views.py
./django_analysis_tool/lab_analysis_tools/visualize.py
./django_analysis_tool/lab_analysis_tools/migrations/__init__.py
./django_analysis_tool/lab_analysis_tools/templatetags/__init__.py
./django_analysis_tool/lab_analysis_tools/templatetags/poll_extras.py
django_analysis_tool/__init__.py
django_analysis_tool/db.sqlite3
django_analysis_tool/manage.py
django_analysis_tool/run.py
django_analysis_tool.egg-info/PKG-INFO
django_analysis_tool.egg-info/SOURCES.txt
django_analysis_tool.egg-info/dependency_links.txt
django_analysis_tool.egg-info/requires.txt
django_analysis_tool.egg-info/top_level.txt
django_analysis_tool/base/__init__.py
django_analysis_tool/base/analyzer.py
django_analysis_tool/base/scanner.py
django_analysis_tool/base/token.py
