Metadata-Version: 1.0
Name: django-analysis-tool
Version: 1.1.21
Summary: Tools to analysis lab task
Home-page:  
Author: creeper
Author-email: creeper@163.com
License: UNKNOWN
Platform: UNKNOWN
